MANIFEST.in
setup.cfg
setup.py
polo/__init__.py
polo/polo.c
polo/polo.pyx
polo/test.py
polo.egg-info/PKG-INFO
polo.egg-info/SOURCES.txt
polo.egg-info/dependency_links.txt
polo.egg-info/requires.txt
polo.egg-info/top_level.txt