Metadata-Version: 1.1
Name: polo
Version: 0.5
Summary: Optimal Linear Ordering of Hierarchical Trees
Home-page: https://github.com/adrianveres/polo
Author: Adrian Veres
Author-email: adrianveres@gmail.com
License: UNKNOWN
Download-URL: https://github.com/adrianveres/polo/tarball/0.1
Keywords: hierarchical,clustering,linear ordering,leaves
Platform: UNKNOWN
